flask_simple_geoip.py
Flask_Simple_GeoIP-0.2.4.dist-info/METADATA
Flask_Simple_GeoIP-0.2.4.dist-info/WHEEL
Flask_Simple_GeoIP-0.2.4.dist-info/top_level.txt
Flask_Simple_GeoIP-0.2.4.dist-info/RECORD
