Metadata-Version: 2.1
Name: Flask-Simple-GeoIP
Version: 0.2.4
Summary: The simplest GeoIP lookup library for Flask.
Home-page: https://github.com/whois-api-llc/flask-simple-geoip
Author: Randall Degges
Author-email: r@rdegges.com
License: BSD
Platform: any
Classifier: Environment :: Web Environment
Classifier: Intended Audience :: Developers
Classifier: License :: OSI Approved :: BSD License
Classifier: Operating System :: OS Independent
Classifier: Programming Language :: Python
Classifier: Topic :: Internet :: WWW/HTTP :: Dynamic Content
Classifier: Topic :: Software Development :: Libraries :: Python Modules
Provides-Extra: test
